automation_framework/__init__.py
automation_framework-0.1.0.dist-info/licenses/LICENSE
automation_framework-0.1.0.dist-info/METADATA
automation_framework-0.1.0.dist-info/WHEEL
automation_framework-0.1.0.dist-info/top_level.txt
automation_framework-0.1.0.dist-info/RECORD
