Metadata-Version: 2.4
Name: automation-framework
Version: 0.1.0
Summary: A Python framework for automation projects
Author-email: Paras <parasdattera555@gmail.com>
License: MIT
Project-URL: Homepage, https://github.com/yourusername/automation-framework
License-File: LICENSE
Dynamic: license-file
